easycrystallography/__init__.py
easycrystallography/Components/AtomicDisplacement.py
easycrystallography/Components/Displacement.py
easycrystallography/Components/Lattice.py
easycrystallography/Components/Site.py
easycrystallography/Components/SpaceGroup.py
easycrystallography/Components/Specie.py
easycrystallography/Components/Susceptibility.py
easycrystallography/Components/Twin.py
easycrystallography/Components/__init__.py
easycrystallography/Databases/__init__.py
easycrystallography/Databases/periodic_table.json
easycrystallography/Databases/symm_data.json
easycrystallography/Databases/symm_ops.json
easycrystallography/Elements/__init__.py
easycrystallography/Elements/periodic_table.py
easycrystallography/Structures/Phase.py
easycrystallography/Structures/__init__.py
easycrystallography/Symmetry/Bonding.py
easycrystallography/Symmetry/SymOp.py
easycrystallography/Symmetry/__init__.py
easycrystallography/Symmetry/functions.py
easycrystallography/Symmetry/groups.py
easycrystallography/Symmetry/tools.py
easycrystallography/io/__init__.py
easycrystallography/io/cif_parser.py
easycrystallography/io/parser.py
easycrystallography/io/star.py
easycrystallography/io/star_base.py
easycrystallography/io/template.py
easycrystallography/io/cif/__init__.py
easycrystallography/io/cif/atoms.py
easycrystallography/io/cif/generic.py
easycrystallography/io/cif/lattice.py
easycrystallography/io/cif/spacegroup.py
easycrystallography/io/cif/structures.py
easycrystallography/io/cif/template.py
easycrystallography-0.9.0.dist-info/METADATA
easycrystallography-0.9.0.dist-info/WHEEL
easycrystallography-0.9.0.dist-info/licenses/LICENSE
easycrystallography-0.9.0.dist-info/RECORD
