Metadata-Version: 2.4
Name: easycrystallography
Version: 0.9.0
Summary: Crystallography in EasyScience
Project-URL: homepage, https://github.com/EasyScience/EasyCrystallography
Project-URL: documentation, https://easyscience.github.io/EasyCrystallography
Project-URL: source, https://github.com/EasyScience/EasyCrystallography
Project-URL: tracker, https://github.com/EasyScience/EasyCrystallography/issues
Author: EasyCrystallography contributors
License: BSD 3-Clause License
License-File: LICENSE
Classifier: Development Status :: 4 - Beta
Classifier: License :: OSI Approved :: BSD License
Classifier: Operating System :: OS Independent
Classifier: Programming Language :: Python :: 3
Classifier: Programming Language :: Python :: 3 :: Only
Classifier: Programming Language :: Python :: 3.11
Classifier: Programming Language :: Python :: 3.12
Classifier: Programming Language :: Python :: 3.13
Classifier: Topic :: Scientific/Engineering
Requires-Python: <3.14,>=3.11
Requires-Dist: asteval
Requires-Dist: easyscience
Requires-Dist: gemmi
Requires-Dist: numpy
Requires-Dist: periodictable
Requires-Dist: uncertainties
Requires-Dist: versioningit
Requires-Dist: xarray
Provides-Extra: dev
Requires-Dist: build; extra == 'dev'
Requires-Dist: pytest; extra == 'dev'
Requires-Dist: pytest-cov; extra == 'dev'
Requires-Dist: pytest-xdist; extra == 'dev'
Requires-Dist: ruff; extra == 'dev'
